PDPParser/__init__.py
PDPParser/pdpparser.py
PDPParser-0.0.4.dist-info/LICENSE
PDPParser-0.0.4.dist-info/METADATA
PDPParser-0.0.4.dist-info/WHEEL
PDPParser-0.0.4.dist-info/top_level.txt
PDPParser-0.0.4.dist-info/RECORD
