Metadata-Version: 2.1
Name: PDPParser
Version: 0.0.4
Summary: Simple package to help parse PDP on Footsites!
Home-page: UNKNOWN
Author: Mrbeastmode
Author-email: UNKNOWN
License: UNKNOWN
Keywords: python,pdp,footlocker
Platform: UNKNOWN
Classifier: Intended Audience :: Developers
Classifier: Programming Language :: Python :: 3
Classifier: Operating System :: Microsoft :: Windows
